{
  "exp_id": "B004_per-axis-grid",
  "type": "baseline",
  "plan_id": "001",
  "started_at": "2026-05-10T01:06:30+09:00",
  "finished_at": "2026-05-10T01:06:34+09:00",
  "duration_sec": 3.285,
  "n_train": 10000,
  "k": 5,
  "cv_mean_eucl": 0.012940614806511989,
  "cv_std_eucl": 0.0005842361694455372,
  "cv_per_axis_mae": [
    0.007047868600000083,
    0.007104491399999957,
    0.005042211699999991
  ],
  "cv_hit_rate": {
    "0.05": 0.9571,
    "0.10": 0.9923,
    "0.20": 1.0,
    "0.50": 1.0
  },
  "oof_summary": {
    "mean_eucl": 0.012940614806511989,
    "median_eucl": 0.008324749397913025,
    "p95_eucl": 0.044799807999127014,
    "max_eucl": 0.1788468890503842,
    "per_axis_mae": [
      0.007047868600000083,
      0.007104491399999955,
      0.00504221169999999
    ],
    "hit_rate": {
      "0.05": 0.9571,
      "0.10": 0.9923,
      "0.20": 1.0,
      "0.50": 1.0
    },
    "n": 10000
  },
  "fold_metrics": [
    {
      "mean_eucl": 0.013708014418274132,
      "median_eucl": 0.008611478313743542,
      "p95_eucl": 0.04655987704618531,
      "max_eucl": 0.1759960338814466,
      "per_axis_mae": [
        0.007177450000000149,
        0.00769821849999995,
        0.005419091499999972
      ],
      "hit_rate": {
        "0.05": 0.954,
        "0.10": 0.99,
        "0.20": 1.0,
        "0.50": 1.0
      },
      "n": 2000,
      "fold": 0,
      "chosen_per_axis": [
        [
          2,
          1
        ],
        [
          2,
          1
        ],
        [
          2,
          1
        ]
      ]
    },
    {
      "mean_eucl": 0.012013516528914518,
      "median_eucl": 0.008057777787056094,
      "p95_eucl": 0.037005048551008904,
      "max_eucl": 0.1788468890503842,
      "per_axis_mae": [
        0.006816968000000049,
        0.006561771499999948,
        0.004356465499999984
      ],
      "hit_rate": {
        "0.05": 0.969,
        "0.10": 0.9935,
        "0.20": 1.0,
        "0.50": 1.0
      },
      "n": 2000,
      "fold": 1,
      "chosen_per_axis": [
        [
          2,
          1
        ],
        [
          2,
          1
        ],
        [
          2,
          1
        ]
      ]
    },
    {
      "mean_eucl": 0.012592367643355258,
      "median_eucl": 0.008042819887443419,
      "p95_eucl": 0.045491897661710114,
      "max_eucl": 0.1662924518701911,
      "per_axis_mae": [
        0.006882177000000076,
        0.00680632349999996,
        0.005047655499999977
      ],
      "hit_rate": {
        "0.05": 0.9575,
        "0.10": 0.9915,
        "0.20": 1.0,
        "0.50": 1.0
      },
      "n": 2000,
      "fold": 2,
      "chosen_per_axis": [
        [
          2,
          1
        ],
        [
          2,
          1
        ],
        [
          2,
          1
        ]
      ]
    },
    {
      "mean_eucl": 0.013131478455669381,
      "median_eucl": 0.008799253266901657,
      "p95_eucl": 0.0432717164219814,
      "max_eucl": 0.1615512266310596,
      "per_axis_mae": [
        0.007328447000000068,
        0.0069698839999999505,
        0.0051488070000000165
      ],
      "hit_rate": {
        "0.05": 0.9585,
        "0.10": 0.992,
        "0.20": 1.0,
        "0.50": 1.0
      },
      "n": 2000,
      "fold": 3,
      "chosen_per_axis": [
        [
          2,
          1
        ],
        [
          2,
          1
        ],
        [
          2,
          1
        ]
      ]
    },
    {
      "mean_eucl": 0.013257696986346651,
      "median_eucl": 0.008167537944343358,
      "p95_eucl": 0.050990164500958855,
      "max_eucl": 0.16801270848658742,
      "per_axis_mae": [
        0.007034301000000072,
        0.007486259499999977,
        0.0052390390000000035
      ],
      "hit_rate": {
        "0.05": 0.9465,
        "0.10": 0.9945,
        "0.20": 1.0,
        "0.50": 1.0
      },
      "n": 2000,
      "fold": 4,
      "chosen_per_axis": [
        [
          2,
          1
        ],
        [
          2,
          1
        ],
        [
          2,
          1
        ]
      ]
    }
  ],
  "config": {
    "exp_id": "B004_per-axis-grid",
    "plan_id": "001",
    "type": "baseline",
    "baseline_id": "B001_linear-2pt",
    "per_axis": "tune",
    "grid": [
      [
        2,
        1
      ],
      [
        3,
        1
      ],
      [
        3,
        2
      ],
      [
        5,
        1
      ],
      [
        5,
        2
      ],
      [
        5,
        3
      ],
      [
        7,
        1
      ],
      [
        7,
        2
      ],
      [
        7,
        3
      ],
      [
        11,
        1
      ],
      [
        11,
        2
      ],
      [
        11,
        3
      ]
    ],
    "t_target": 80,
    "k": 5,
    "seed": 42
  },
  "final_chosen_per_axis": [
    [
      2,
      1
    ],
    [
      2,
      1
    ],
    [
      2,
      1
    ]
  ],
  "fold_chosen_per_axis": [
    [
      [
        2,
        1
      ],
      [
        2,
        1
      ],
      [
        2,
        1
      ]
    ],
    [
      [
        2,
        1
      ],
      [
        2,
        1
      ],
      [
        2,
        1
      ]
    ],
    [
      [
        2,
        1
      ],
      [
        2,
        1
      ],
      [
        2,
        1
      ]
    ],
    [
      [
        2,
        1
      ],
      [
        2,
        1
      ],
      [
        2,
        1
      ]
    ],
    [
      [
        2,
        1
      ],
      [
        2,
        1
      ],
      [
        2,
        1
      ]
    ]
  ],
  "full_train_grid_errors": {
    "0": {
      "w2d1": 0.007047868600000092,
      "w3d1": 0.008710024083333217,
      "w3d2": 0.01052089510000003,
      "w5d1": 0.012654290840000125,
      "w5d2": 0.011211218219999998,
      "w5d3": 0.017669268579957806,
      "w7d1": 0.016930352764285807,
      "w7d2": 0.013565641857142818,
      "w7d3": 0.01681646614285797,
      "w11d1": 0.025025104390000007,
      "w11d2": 0.01887588102908962,
      "w11d3": 0.019653762987878697
    },
    "1": {
      "w2d1": 0.007104491399999937,
      "w3d1": 0.0087057368166667,
      "w3d2": 0.011005569099999916,
      "w5d1": 0.012211957359999973,
      "w5d2": 0.011014974359999976,
      "w5d3": 0.018032150220004796,
      "w7d1": 0.015982826924999905,
      "w7d2": 0.013428296392857107,
      "w7d3": 0.01633442425714271,
      "w11d1": 0.02337622402090915,
      "w11d2": 0.017954295280000063,
      "w11d3": 0.019382986403030218
    },
    "2": {
      "w2d1": 0.0050422116999999985,
      "w3d1": 0.005925474600000019,
      "w3d2": 0.008520245899999926,
      "w5d1": 0.008161910940000017,
      "w5d2": 0.007604667379999975,
      "w5d3": 0.01336414230001091,
      "w7d1": 0.01036421773928564,
      "w7d2": 0.008787843200000051,
      "w7d3": 0.011446372364285468,
      "w11d1": 0.014380974541818171,
      "w11d2": 0.011929673976362947,
      "w11d3": 0.012391525509090937
    }
  }
}